jupyter_addons/__init__.py
nummath/__init__.py
nummath/deriv.py
nummath/euler.py
nummath/graphing.py
nummath/graphing2.py
nummath/integration.py
nummath/interpolation.py
nummath/linear_system.py
nummath/ode.py
nummath/polynomial.py
nummath/roots.py
pypeflow/__init__.py
pypeflow/analysis/__init__.py
pypeflow/analysis/analysis.py
pypeflow/analysis/network.py
pypeflow/core/__init__.py
pypeflow/core/cross_sections.py
pypeflow/core/fitting.py
pypeflow/core/flow_coefficient.py
pypeflow/core/fluids.py
pypeflow/core/pipe.py
pypeflow/core/pipe_schedules.py
pypeflow/core/pump.py
pypeflow/core/resistance_coefficient.py
pypeflow/core/valves.py
pypeflow/design/__init__.py
pypeflow/design/design.py
pypeflow/design/network.py
pypeflow/utils/__init__.py
pypeflow/utils/misc.py
pypeflow/utils/pump_curve.py
pypeflow/utils/system_curve.py
quantities/__init__.py
quantities/base.py
quantities/definitions.py
tc_pypeflow-2020.2.dist-info/LICENSE
tc_pypeflow-2020.2.dist-info/METADATA
tc_pypeflow-2020.2.dist-info/WHEEL
tc_pypeflow-2020.2.dist-info/top_level.txt
tc_pypeflow-2020.2.dist-info/RECORD
