Metadata-Version: 2.1
Name: tc-pypeflow
Version: 2020.2
Summary: piping network design and analysis
Home-page: https://github.com/TomLXXVI/pypeflow
Author: Tom Christiaens
Author-email: tom.chr@proximus.be
License: MIT License
Platform: UNKNOWN
Requires-Dist: numpy (>=1.17.1)
Requires-Dist: matplotlib (>=3.1.1)
Requires-Dist: CoolProp (>=6.3.0)
Requires-Dist: pandas (>=0.25.1)
Requires-Dist: ipython (>=7.8.0)
Requires-Dist: setuptools (>=46.1.3)
